python_package/__init__.py
python_package/hello_world.py
avwrapper-0.0.2rc14.post1.dist-info/LICENSE
avwrapper-0.0.2rc14.post1.dist-info/WHEEL
avwrapper-0.0.2rc14.post1.dist-info/METADATA
avwrapper-0.0.2rc14.post1.dist-info/RECORD
